Metadata-Version: 2.1
Name: darkhan
Version: 0.1
Summary: desc
Author-email: erdauletov.1512@gmail.com
